cgal-6.0.post202410021207.dist-info/RECORD
cgal-6.0.post202410021207.dist-info/LICENSE.GPL
cgal-6.0.post202410021207.dist-info/WHEEL
cgal-6.0.post202410021207.dist-info/LICENSE.COMMERCIAL
cgal-6.0.post202410021207.dist-info/top_level.txt
cgal-6.0.post202410021207.dist-info/METADATA
CGAL/CGAL_Classification.py
CGAL/_CGAL_Convex_hull_3.so
CGAL/CGAL_Point_set_processing_3.py
CGAL/_CGAL_Voronoi_diagram_2.so
CGAL/_CGAL_Convex_hull_2.so
CGAL/CGAL_HalfedgeDS.py
CGAL/CGAL_Point_set_3.py
CGAL/_CGAL_Alpha_shape_2.so
CGAL/CGAL_Advancing_front_surface_reconstruction.py
CGAL/_CGAL_Polyhedron_3.so
CGAL/CGAL_Kernel.py
CGAL/CGAL_Alpha_shape_2.py
CGAL/CGAL_Triangulation_2.py
CGAL/CGAL_Polygon_mesh_processing.py
CGAL/CGAL_Alpha_wrap_3.py
CGAL/CGAL_Convex_hull_2.py
CGAL/_CGAL_Mesh_3.so
CGAL/CGAL_Surface_mesher.py
CGAL/CGAL_Box_intersection_d.py
CGAL/_CGAL_Advancing_front_surface_reconstruction.so
CGAL/CGAL_Convex_hull_3.py
CGAL/_CGAL_Mesh_2.so
CGAL/_CGAL_Shape_detection.so
CGAL/__init__.py
CGAL/CGAL_Spatial_searching.py
CGAL/_CGAL_AABB_tree.so
CGAL/CGAL_Triangulation_3.py
CGAL/CGAL_Voronoi_diagram_2.py
CGAL/_CGAL_Point_set_processing_3.so
CGAL/_CGAL_Triangulation_3.so
CGAL/CGAL_Polyhedron_3.py
CGAL/_CGAL_Interpolation.so
CGAL/_CGAL_Classification.so
CGAL/CGAL_Shape_detection.py
CGAL/_CGAL_Triangulation_2.so
CGAL/_CGAL_HalfedgeDS.so
CGAL/_CGAL_Polyline_simplification_2.so
CGAL/_CGAL_Kernel.so
CGAL/_CGAL_Polygon_mesh_processing.so
CGAL/_CGAL_Surface_mesher.so
CGAL/CGAL_Mesh_3.py
CGAL/CGAL_AABB_tree.py
CGAL/_CGAL_Spatial_searching.so
CGAL/_CGAL_Box_intersection_d.so
CGAL/CGAL_Mesh_2.py
CGAL/_CGAL_Point_set_3.so
CGAL/_CGAL_Alpha_wrap_3.so
CGAL/CGAL_Polyline_simplification_2.py
CGAL/CGAL_Interpolation.py
CGAL/.dylibs/libgmpxx.4.dylib
CGAL/.dylibs/libboost_iostreams.dylib
CGAL/.dylibs/libtbbmalloc.2.13.dylib
CGAL/.dylibs/libc++.1.0.dylib
CGAL/.dylibs/liblas.dylib
CGAL/.dylibs/libbz2.1.0.8.dylib
CGAL/.dylibs/libz.1.3.1.dylib
CGAL/.dylibs/libboost_serialization.dylib
CGAL/.dylibs/libzstd.1.5.6.dylib
CGAL/.dylibs/libtbb.12.13.dylib
CGAL/.dylibs/liblzma.5.dylib
CGAL/.dylibs/libgmp.10.dylib
CGAL/.dylibs/libmpfr.6.dylib
lib/libCGAL_Surface_mesher_cpp.dylib
lib/libCGAL_Kernel_cpp.dylib
