Metadata-Version: 2.1
Name: cgal
Version: 6.0.post202410021207
Summary: CGAL bindings, allowing to use some of the CGAL library in Python.
Home-page: https://github.com/CGAL/cgal-swig-bindings
Author: CGAL Project
Classifier: Development Status :: 5 - Production/Stable
Classifier: Environment :: Console
Classifier: Intended Audience :: Developers
Classifier: License :: OSI Approved :: GNU General Public License v3 or later (GPLv3+)
Classifier: Natural Language :: English
Classifier: Operating System :: MacOS :: MacOS X
Classifier: Operating System :: Microsoft :: Windows
Classifier: Operating System :: Unix
Classifier: Programming Language :: C++
Classifier: Programming Language :: Python :: 3
Classifier: Topic :: Scientific/Engineering
Classifier: Topic :: Scientific/Engineering :: Mathematics
Classifier: Topic :: Software Development :: Libraries
Requires-Python: >=3.6
License-File: LICENSE.COMMERCIAL
License-File: LICENSE.GPL
Requires-Dist: numpy
